{
  "city": [
    { "state": "Andhra Pradesh", "data": ["Vijayawada", "Guntur", "Nellore"] },
    { "state": "Telangana", "data": ["Hyderabad", "Suryapet"] },
    { "state": "Maharastra", "data": ["Mumbai"] }
  ],
  "brands": [
    { "name": "apollo abc", "image": "/sda" },
    { "name": "apollo xyz", "image": "/das" },
    { "name": "apollo spectra", "image": "/sds" },
    { "name": "apollo pharma", "image": "/sas" }
  ],
  "experience": [{ "name": "0-5" }, { "name": "5-10" }, { "name": "11 - 15" }, { "name": "15+" }],
  "availability": [
    { "name": "Now" },
    { "name": "Today" },
    { "name": "Tomorrow" },
    { "name": "Next 3 Days" }
  ],
  "fee": [{ "name": "0-500" }, { "name": "500-1000" }, { "name": "501-1000" }, { "name": "1000+" }],
  "gender": [{ "name": "MALE" }, { "name": "FEMALE" }],
  "language": [{ "name": "Hindi" }, { "name": "English" }, { "name": "Telugu" }]
}
